catcher_modules/__init__.py
catcher_modules/cache/__init__.py
catcher_modules/cache/redis.py
catcher_modules/database/__init__.py
catcher_modules/database/couchbase.py
catcher_modules/database/mongo.py
catcher_modules/database/mssql.py
catcher_modules/database/mysql.py
catcher_modules/database/oracle.py
catcher_modules/database/postgres.py
catcher_modules/database/sqlite.py
catcher_modules/exceptions/__init__.py
catcher_modules/exceptions/airflow_exceptions.py
catcher_modules/frontend/__init__.py
catcher_modules/frontend/selenium.py
catcher_modules/marketing/__init__.py
catcher_modules/marketing/marketo.py
catcher_modules/mq/__init__.py
catcher_modules/mq/kafka.py
catcher_modules/mq/rabbit.py
catcher_modules/pipeline/__init__.py
catcher_modules/pipeline/airflow.py
catcher_modules/pipeline/airflow_utils/__init__.py
catcher_modules/pipeline/airflow_utils/airflow_client.py
catcher_modules/pipeline/airflow_utils/airflow_db_client.py
catcher_modules/service/__init__.py
catcher_modules/service/docker.py
catcher_modules/service/elastic.py
catcher_modules/service/email.py
catcher_modules/service/expect.py
catcher_modules/service/prepare.py
catcher_modules/service/s3.py
catcher_modules/service/salesforce.py
catcher_modules/service/comparator/__init__.py
catcher_modules/service/comparator/avro_comparator.py
catcher_modules/service/comparator/csv_comparator.py
catcher_modules/service/comparator/parquet_comparator.py
catcher_modules/utils/__init__.py
catcher_modules/utils/db_utils.py
catcher_modules/utils/generator_utils.py
catcher_modules/utils/module_utils.py
test/__init__.py
test/abs_test_class.py
test/airflow_test.py
test/docker_test.py
test/elastic_test.py
test/expect_test.py
test/kafka_test.py
test/marketo_test.py
test/migration_test.py
test/mongo_test.py
test/mssql_test.py
test/mysql_test.py
test/postgres_test.py
test/prepare_test.py
test/rabbit_test.py
test/redis_test.py
test/s3_test.py
test/selenium_test.py
test/sqlite_test.py
test/test_utils.py
catcher_modules-6.0.7.dist-info/LICENSE
catcher_modules-6.0.7.dist-info/METADATA
catcher_modules-6.0.7.dist-info/WHEEL
catcher_modules-6.0.7.dist-info/top_level.txt
catcher_modules-6.0.7.dist-info/RECORD
